edgepy/Disp.py
edgepy/__init__.py
edgepy/makelib.py
edgepy/ref.py
edgepy/util.py
edgepy/docs/counts/empty.txt
edgepy/docs/genelib/empty.txt
edgepy/docs/info/empty.txt
edgepy/docs/plots/empty.txt
edgepy/docs/results/empty.txt
edgepy/docs/rfiles/calcdisp.R
edgepy/docs/rfiles/empty.txt
edgepy/docs/trimmed_results/empty.txt
edgepy/docs/workspace/empty.txt
edgepy-0.1.33.dev0.dist-info/LICENSE.txt
edgepy-0.1.33.dev0.dist-info/METADATA
edgepy-0.1.33.dev0.dist-info/WHEEL
edgepy-0.1.33.dev0.dist-info/top_level.txt
edgepy-0.1.33.dev0.dist-info/RECORD
