Metadata-Version: 2.1
Name: edgepy
Version: 0.1.33.dev0
Summary: UNKNOWN
Home-page: http://pypi.python.org/pypi/edgepy/
Author: Alex Summers
Author-email: asummers.edgepy@gmail.com
License: LICENSE.txt
Platform: UNKNOWN
Requires-Dist: biopython (>=1.71)
Requires-Dist: numpy
Requires-Dist: pandas
Requires-Dist: bcbio-gff
